Workbook

Sheet Live Data
B1: AURUM KOREA — LIVE MARKET DATA
B2: Data Pulled: 2026-04-11 23:26 UTC
B4: INTERNATIONAL GOLD SPOT (XAU/USD)
B5: Source | C5: Value | D5: Unit | E5: Timestamp
B6: JM Bullion — Spot Price | C6: 4762.62 | D6: USD / troy oz | E6: Apr 11, 2026 8:37 AM EDT
B7: Spot Price per Gram | C7: =C6/31.1035 | D7: USD / gram | E7: Calculated (÷ 31.1035)
B8: Spot Price per Don (3.75g) | C8: =C7*3.75 | D8: USD / don | E8: Calculated (× 3.75)
B10: FOREIGN EXCHANGE RATES
B11: Source | C11: Rate | D11: Pair | E11: Timestamp
B12: ExchangeRate-API (Live) | C12: 1482.8 | D12: KRW per USD | E12: Apr 11, 2026
B13: ExchangeRate-API (Live) | C13: 1.2737 | D13: SGD per USD | E13: Apr 11, 2026
B15: KOREAN RETAIL GOLD PRICES (1돈 = 3.75g, 24K)
B16: Source | C16: 살 때 (Buy) | D16: 팔 때 (Sell) | E16: Notes
B17: 한국금거래소 (Korea Gold Exchange) | C17: 994000 | D17: 833000 | E17: CBC News, Apr 11 2026
B18: 금시세닷컴 (GoldPrice.com KR) | C18: 988000 | D18: 840000 | E18: CBC News, Apr 11 2026
B19: DailyLifeData Benchmark (no VAT/premium) | C19: 849035 | D19: — | E19: KRX-aligned reference, Apr 11
B20: Average Korean Retail (살 때) | C20: =AVERAGE(C17,C18) | D20: =AVERAGE(D17,D18) | E20: Used in core analysis

Sheet Core Analysis
B1: KR RETAIL vs US SPOT+5% — MARGIN COMPARISON
B2: All prices converted to USD per gram for apples-to-apples comparison
B4: SIDE-BY-SIDE: $/GRAM COMPARISON
C5: 🇰🇷 Korean Retail | D5: 🇺🇸 US Spot + 5% | E5: Δ Difference | F5: Δ %
B6: Price per Don (₩) | C6: ='Live Data'!C20 | D6: ='Live Data'!C8*1.05*'Live Data'!C12 | E6: =C6-D6 | F6: =E6/D6
B7: Price per Don (USD) | C7: =C6/'Live Data'!C12 | D7: ='Live Data'!C8*1.05 | E7: =C7-D7 | F7: =E7/D7
B8: Price per Gram (USD) | C8: =C7/3.75 | D8: ='Live Data'!C7*1.05 | E8: =C8-D8 | F8: =E8/D8
B9: Price per Troy Oz (USD) | C9: =C8*31.1035 | D9: ='Live Data'!C6*1.05 | E9: =C9-D9 | F9: =E9/D9
B11: KOREAN RETAIL PREMIUM BREAKDOWN
B12: Component | C12: ₩ per Don | D12: $ per Don | E12: $ per Gram | F12: % of Final
B13: ① Raw International Spot (XAU→KRW) | C13: ='Live Data'!C19 | D13: =C13/'Live Data'!C12 | E13: =D13/3.75 | F13: =C13/'Live Data'!C20
B14: ② Dealer Spread + Making Charges (공임) | C14: ='Live Data'!C20/1.1-'Live Data'!C19 | D14: =C14/'Live Data'!C12 | E14: =D14/3.75 | F14: =C14/'Live Data'!C20
B15: ③ VAT (10% on retail, non-KRX) | C15: ='Live Data'!C20-'Live Data'!C20/1.1 | D15: =C15/'Live Data'!C12 | E15: =D15/3.75 | F15: =C15/'Live Data'!C20
B16: TOTAL = Korean Retail Price (살 때) | C16: =SUM(C13:C15) | D16: =SUM(D13:D15) | E16: =SUM(E13:E15) | F16: =SUM(F13:F15)
B18: AURUM KOREA PRICE ADVANTAGE (vs Korean Retail)
B19: Aurum Premium Tier | C19: Premium % | D19: Aurum $/gram | E19: KR Retail $/gram | F19: Customer Saves $/gram
B20: Wire Transfer (2.5%) | C20: 0.025 | D20: ='Live Data'!C7*(1+C20) | E20: =C8 | F20: =E20-D20
B21: Credit Card (5.5%) | C21: 0.055 | D21: ='Live Data'!C7*(1+C21) | E21: =C8 | F21: =E21-D21
B22: Crypto (2.0%) | C22: 0.02 | D22: ='Live Data'!C7*(1+C22) | E22: =C8 | F22: =E22-D22
B23: ★ Requested Test: Spot + 5.0% | C23: 0.05 | D23: ='Live Data'!C7*(1+C23) | E23: =C8 | F23: =E23-D23
B25: CUSTOMER SAVINGS % (vs Korean Retail)
B26: Wire (2.5%) — Customer saves | C26: =F20/E20 | E26: per gram | F26: =F20*31.1035
B27: Card (5.5%) — Customer saves | C27: =F21/E21 | E27: per gram | F27: =F21*31.1035
B28: Crypto (2.0%) — Customer saves | C28: =F22/E22 | E28: per gram | F28: =F22*31.1035
B29: ★ Spot + 5% — Customer saves | C29: =F23/E23 | E29: per gram | F29: =F23*31.1035

Sheet Sensitivity
B1: SENSITIVITY: PREMIUM & FX SCENARIOS
B3: SCENARIO A: AURUM PREMIUM vs CUSTOMER SAVINGS ($/gram)
B4: Aurum Premium % | C4: Aurum $/gram | D4: KR Retail $/gram | E4: Saving $/gram | F4: Saving % | G4: Saving $/oz
B5: 0.015 | C5: ='Live Data'!C7*(1+B5) | D5: ='Core Analysis'!C8 | E5: =D5-C5 | F5: =E5/D5 | G5: =E5*31.1035
B6: 0.02 | C6: ='Live Data'!C7*(1+B6) | D6: ='Core Analysis'!C8 | E6: =D6-C6 | F6: =E6/D6 | G6: =E6*31.1035
B7: 0.025 | C7: ='Live Data'!C7*(1+B7) | D7: ='Core Analysis'!C8 | E7: =D7-C7 | F7: =E7/D7 | G7: =E7*31.1035
B8: 0.03 | C8: ='Live Data'!C7*(1+B8) | D8: ='Core Analysis'!C8 | E8: =D8-C8 | F8: =E8/D8 | G8: =E8*31.1035
B9: 0.035 | C9: ='Live Data'!C7*(1+B9) | D9: ='Core Analysis'!C8 | E9: =D9-C9 | F9: =E9/D9 | G9: =E9*31.1035
B10: 0.04 | C10: ='Live Data'!C7*(1+B10) | D10: ='Core Analysis'!C8 | E10: =D10-C10 | F10: =E10/D10 | G10: =E10*31.1035
B11: 0.045 | C11: ='Live Data'!C7*(1+B11) | D11: ='Core Analysis'!C8 | E11: =D11-C11 | F11: =E11/D11 | G11: =E11*31.1035
B12: 0.05 | C12: ='Live Data'!C7*(1+B12) | D12: ='Core Analysis'!C8 | E12: =D12-C12 | F12: =E12/D12 | G12: =E12*31.1035
B13: 0.055 | C13: ='Live Data'!C7*(1+B13) | D13: ='Core Analysis'!C8 | E13: =D13-C13 | F13: =E13/D13 | G13: =E13*31.1035
B14: 0.06 | C14: ='Live Data'!C7*(1+B14) | D14: ='Core Analysis'!C8 | E14: =D14-C14 | F14: =E14/D14 | G14: =E14*31.1035
B15: 0.07 | C15: ='Live Data'!C7*(1+B15) | D15: ='Core Analysis'!C8 | E15: =D15-C15 | F15: =E15/D15 | G15: =E15*31.1035
B16: 0.08 | C16: ='Live Data'!C7*(1+B16) | D16: ='Core Analysis'!C8 | E16: =D16-C16 | F16: =E16/D16 | G16: =E16*31.1035
B17: 0.1 | C17: ='Live Data'!C7*(1+B17) | D17: ='Core Analysis'!C8 | E17: =D17-C17 | F17: =E17/D17 | G17: =E17*31.1035
B20: SCENARIO B: FX SENSITIVITY (KRW/USD) — Impact on KR Retail $/gram at 5% Aurum Premium
B21: KRW/USD Rate | C21: KR Retail $/don | D21: KR Retail $/gram | E21: Aurum $/gram (5%) | F21: Δ $/gram | G21: Advantage %
B22: 1350 | C22: ='Live Data'!C20/B22 | D22: =C22/3.75 | E22: ='Live Data'!C7*1.05 | F22: =D22-E22 | G22: =F22/D22
B23: 1400 | C23: ='Live Data'!C20/B23 | D23: =C23/3.75 | E23: ='Live Data'!C7*1.05 | F23: =D23-E23 | G23: =F23/D23
B24: 1450 | C24: ='Live Data'!C20/B24 | D24: =C24/3.75 | E24: ='Live Data'!C7*1.05 | F24: =D24-E24 | G24: =F24/D24
B25: 1482.8 | C25: ='Live Data'!C20/B25 | D25: =C25/3.75 | E25: ='Live Data'!C7*1.05 | F25: =D25-E25 | G25: =F25/D25
B26: 1500 | C26: ='Live Data'!C20/B26 | D26: =C26/3.75 | E26: ='Live Data'!C7*1.05 | F26: =D26-E26 | G26: =F26/D26
B27: 1550 | C27: ='Live Data'!C20/B27 | D27: =C27/3.75 | E27: ='Live Data'!C7*1.05 | F27: =D27-E27 | G27: =F27/D27
B28: 1600 | C28: ='Live Data'!C20/B28 | D28: =C28/3.75 | E28: ='Live Data'!C7*1.05 | F28: =D28-E28 | G28: =F28/D28
B29: 1650 | C29: ='Live Data'!C20/B29 | D29: =C29/3.75 | E29: ='Live Data'!C7*1.05 | F29: =D29-E29 | G29: =F29/D29

Sheet Assumptions
B1: ASSUMPTIONS & DATA SOURCES
B3: GOLD SPOT PRICE
B4: Source | C4: JM Bullion live spot — jmbullion.com/charts/gold-price/
B5: Price | C5: $4,762.62 / troy oz as of Apr 11, 2026 8:37 AM EDT
B6: Conversion | C6: 1 troy ounce = 31.1035 grams
B8: FOREIGN EXCHANGE
B9: Source | C9: ExchangeRate-API — open.er-api.com/v6/latest/USD
B10: USD/KRW | C10: 1,482.80 (Apr 11, 2026)
B11: USD/SGD | C11: 1.2737 (Apr 11, 2026)
B13: KOREAN RETAIL GOLD
B14: Source 1 | C14: 한국금거래소 via CBC News — cbci.co.kr (Apr 11, 2026)
B15: Source 2 | C15: 금시세닷컴 via CBC News — cbci.co.kr (Apr 11, 2026)
B16: Benchmark | C16: DailyLifeData.com — KRX-aligned 24K reference (Apr 11, 2026)
B17: 살 때 Price | C17: ₩994,000 (한국금거래소) / ₩988,000 (금시세닷컴) per don
B18: VAT Treatment | C18: 10% VAT included in Korean retail prices (non-KRX purchases)
B19: KRX Route | C19: 0% VAT — available for investment gold via Korea Exchange
B21: KOREAN GOLD UNITS
B22: 1 Don (돈) | C22: =3.75 grams
B23: 1 Nyang (냥) | C23: =37.5 grams = 10 don
B24: 1 Troy Ounce | C24: =31.1035 grams = 8.294 don
B26: AURUM KOREA PREMIUMS
B27: Wire Transfer | C27: 2.5% over international spot
B28: Credit Card | C28: 5.5% over international spot
B29: Crypto | C29: 2.0% over international spot
B30: Requested Test | C30: 5.0% over international spot
B32: KEY ASSUMPTIONS
B33: Korean retail includes | C33: VAT (10%), dealer spread, making charges (공임)
B34: Aurum price is | C34: International spot + premium only (no VAT, no 공임)
B35: FX conversion | C35: Real-time USD/KRW at 1,482.80
B36: Comparison basis | C36: USD per gram, apples-to-apples
